setup.py
vcssshd.py
vcssshd.egg-info/PKG-INFO
vcssshd.egg-info/SOURCES.txt
vcssshd.egg-info/dependency_links.txt
vcssshd.egg-info/not-zip-safe
vcssshd.egg-info/requires.txt
vcssshd.egg-info/top_level.txt