Metadata-Version: 1.0
Name: vcssshd
Version: 0.2.3
Summary: Library for easy and fast creation of an ssh demon for popular VCSs (Mercurial and Git)
Home-page: https://bitbucket.org/ellersseer/vcssshd-lib
Author: Dmitry Zhiltsov
Author-email: dzhiltsov@me.com
License: BSD
Platform: any
Classifier: Environment :: No Input/Output (Daemon)
Classifier: Intended Audience :: Developers
Classifier: License :: OSI Approved :: BSD License
Classifier: Operating System :: POSIX
Classifier: Programming Language :: Python
Classifier: Framework :: Twisted
Classifier: Topic :: Software Development :: Libraries :: Python Modules
